auto_ohin/__init__.py
auto_ohin/main.py
auto_ohin/ohin.py
auto_ohin/overlay_pdf_maker.py
auto_ohin-0.1.0.dist-info/LICENSE.md
auto_ohin-0.1.0.dist-info/METADATA
auto_ohin-0.1.0.dist-info/WHEEL
auto_ohin-0.1.0.dist-info/entry_points.txt
auto_ohin-0.1.0.dist-info/top_level.txt
auto_ohin-0.1.0.dist-info/RECORD
