Metadata-Version: 2.1
Name: auto-ohin
Version: 0.1.0
Summary: You can ohin on the input pdf easily.
Home-page: https://github.com/MitawaUT/auto-ohin
Author: mitawaut
Author-email: so.misawa.research@gmail.com
License: MIT
Keywords: auto-ohin auto_ohin autoohin
Platform: UNKNOWN
Classifier: License :: OSI Approved :: MIT License
Classifier: Programming Language :: Python :: 3.7
Requires-Dist: Pillow
Requires-Dist: reportlab
Requires-Dist: PyPDF4
Requires-Dist: jsonnet
